{
  "svg": {
    "width": 1100,
    "height": 500
  },
  "axes": [
    {
      "orient": "bottom",
      "innerTickSize": 6,
      "outerTickSize": 1,
      "tickPadding": 3,
      "tickArguments": {"0": 20},
      "tickValues": null,
      "ticks": [
        "1950-01-01T08:00:00.000Z",
        "1955-01-01T08:00:00.000Z",
        "1960-01-01T08:00:00.000Z",
        "1965-01-01T08:00:00.000Z",
        "1970-01-01T08:00:00.000Z",
        "1975-01-01T08:00:00.000Z",
        "1980-01-01T08:00:00.000Z",
        "1985-01-01T08:00:00.000Z",
        "1990-01-01T08:00:00.000Z",
        "1995-01-01T08:00:00.000Z",
        "2000-01-01T08:00:00.000Z",
        "2005-01-01T08:00:00.000Z",
        "2010-01-01T08:00:00.000Z",
        "2015-01-01T08:00:00.000Z",
        "2020-01-01T08:00:00.000Z",
        "2025-01-01T08:00:00.000Z",
        "2030-01-01T08:00:00.000Z",
        "2035-01-01T08:00:00.000Z",
        "2040-01-01T08:00:00.000Z",
        "2045-01-01T08:00:00.000Z",
        "2050-01-01T08:00:00.000Z"
      ],
      "axis": "xaxis",
      "scaleDomain": [
        1950,
        2050
      ],
      "offset": {
        "x": 50,
        "y": 450
      },
      "scaleRange": [
        50,
        850
      ],
      "boundingBox": {
        "height": 20.53125,
        "width": 824,
        "y": 450,
        "x": 38
      }
    },
    {
      "orient": "right",
      "innerTickSize": 6,
      "outerTickSize": 1,
      "tickPadding": 3,
      "tickArguments": [10],
      "tickValues": null,
      "ticks": [
        0,
        1000000000,
        2000000000,
        3000000000,
        4000000000,
        5000000000,
        6000000000,
        7000000000,
        8000000000,
        9000000000
      ],
      "axis": "yaxis",
      "scaleDomain": [
        0,
        9242083546
      ],
      "offset": {
        "x": 850,
        "y": 50
      },
      "scaleRange": [
        450,
        50
      ],
      "boundingBox": {
        "height": 406.84375,
        "width": 78,
        "y": 50,
        "x": 850
      }
    }
  ],
  "groups": [
    {
      "schema": [
        "year",
        "population",
        "deconID"
      ],
      "nodeType": "rect",
      "ids": [
        2,
        4,
        6,
        8,
        10,
        12,
        14,
        16,
        18,
        20,
        22,
        24,
        26,
        28,
        30,
        32,
        34,
        36,
        38,
        40,
        42,
        44,
        46,
        48,
        50,
        52,
        54,
        56,
        58,
        60,
        62,
        64,
        66,
        68,
        70,
        72,
        74,
        76,
        78,
        80,
        82,
        84,
        86,
        88,
        90,
        92,
        94,
        96,
        98,
        100,
        102,
        104,
        106,
        108,
        110,
        112,
        114,
        116,
        118,
        120,
        122,
        124,
        126,
        128,
        130,
        132,
        134,
        136,
        138,
        140,
        142,
        144,
        146,
        148,
        150,
        152,
        154,
        156,
        158,
        160,
        162,
        164,
        166,
        168,
        170,
        172,
        174,
        176,
        178,
        180,
        182,
        184,
        186,
        188,
        190,
        192,
        194,
        196,
        198,
        200
      ],
      "data": {
        "year": [
          "Sun Jan 01 1950 00:00:00 GMT-0800 (PST)",
          "Mon Jan 01 1951 00:00:00 GMT-0800 (PST)",
          "Tue Jan 01 1952 00:00:00 GMT-0800 (PST)",
          "Thu Jan 01 1953 00:00:00 GMT-0800 (PST)",
          "Fri Jan 01 1954 00:00:00 GMT-0800 (PST)",
          "Sat Jan 01 1955 00:00:00 GMT-0800 (PST)",
          "Sun Jan 01 1956 00:00:00 GMT-0800 (PST)",
          "Tue Jan 01 1957 00:00:00 GMT-0800 (PST)",
          "Wed Jan 01 1958 00:00:00 GMT-0800 (PST)",
          "Thu Jan 01 1959 00:00:00 GMT-0800 (PST)",
          "Fri Jan 01 1960 00:00:00 GMT-0800 (PST)",
          "Sun Jan 01 1961 00:00:00 GMT-0800 (PST)",
          "Mon Jan 01 1962 00:00:00 GMT-0800 (PST)",
          "Tue Jan 01 1963 00:00:00 GMT-0800 (PST)",
          "Wed Jan 01 1964 00:00:00 GMT-0800 (PST)",
          "Fri Jan 01 1965 00:00:00 GMT-0800 (PST)",
          "Sat Jan 01 1966 00:00:00 GMT-0800 (PST)",
          "Sun Jan 01 1967 00:00:00 GMT-0800 (PST)",
          "Mon Jan 01 1968 00:00:00 GMT-0800 (PST)",
          "Wed Jan 01 1969 00:00:00 GMT-0800 (PST)",
          "Thu Jan 01 1970 00:00:00 GMT-0800 (PST)",
          "Fri Jan 01 1971 00:00:00 GMT-0800 (PST)",
          "Sat Jan 01 1972 00:00:00 GMT-0800 (PST)",
          "Mon Jan 01 1973 00:00:00 GMT-0800 (PST)",
          "Tue Jan 01 1974 00:00:00 GMT-0800 (PST)",
          "Wed Jan 01 1975 00:00:00 GMT-0800 (PST)",
          "Thu Jan 01 1976 00:00:00 GMT-0800 (PST)",
          "Sat Jan 01 1977 00:00:00 GMT-0800 (PST)",
          "Sun Jan 01 1978 00:00:00 GMT-0800 (PST)",
          "Mon Jan 01 1979 00:00:00 GMT-0800 (PST)",
          "Tue Jan 01 1980 00:00:00 GMT-0800 (PST)",
          "Thu Jan 01 1981 00:00:00 GMT-0800 (PST)",
          "Fri Jan 01 1982 00:00:00 GMT-0800 (PST)",
          "Sat Jan 01 1983 00:00:00 GMT-0800 (PST)",
          "Sun Jan 01 1984 00:00:00 GMT-0800 (PST)",
          "Tue Jan 01 1985 00:00:00 GMT-0800 (PST)",
          "Wed Jan 01 1986 00:00:00 GMT-0800 (PST)",
          "Thu Jan 01 1987 00:00:00 GMT-0800 (PST)",
          "Fri Jan 01 1988 00:00:00 GMT-0800 (PST)",
          "Sun Jan 01 1989 00:00:00 GMT-0800 (PST)",
          "Mon Jan 01 1990 00:00:00 GMT-0800 (PST)",
          "Tue Jan 01 1991 00:00:00 GMT-0800 (PST)",
          "Wed Jan 01 1992 00:00:00 GMT-0800 (PST)",
          "Fri Jan 01 1993 00:00:00 GMT-0800 (PST)",
          "Sat Jan 01 1994 00:00:00 GMT-0800 (PST)",
          "Sun Jan 01 1995 00:00:00 GMT-0800 (PST)",
          "Mon Jan 01 1996 00:00:00 GMT-0800 (PST)",
          "Wed Jan 01 1997 00:00:00 GMT-0800 (PST)",
          "Thu Jan 01 1998 00:00:00 GMT-0800 (PST)",
          "Fri Jan 01 1999 00:00:00 GMT-0800 (PST)",
          "Sat Jan 01 2000 00:00:00 GMT-0800 (PST)",
          "Mon Jan 01 2001 00:00:00 GMT-0800 (PST)",
          "Tue Jan 01 2002 00:00:00 GMT-0800 (PST)",
          "Wed Jan 01 2003 00:00:00 GMT-0800 (PST)",
          "Thu Jan 01 2004 00:00:00 GMT-0800 (PST)",
          "Sat Jan 01 2005 00:00:00 GMT-0800 (PST)",
          "Sun Jan 01 2006 00:00:00 GMT-0800 (PST)",
          "Mon Jan 01 2007 00:00:00 GMT-0800 (PST)",
          "Tue Jan 01 2008 00:00:00 GMT-0800 (PST)",
          "Thu Jan 01 2009 00:00:00 GMT-0800 (PST)",
          "Fri Jan 01 2010 00:00:00 GMT-0800 (PST)",
          "Sat Jan 01 2011 00:00:00 GMT-0800 (PST)",
          "Sun Jan 01 2012 00:00:00 GMT-0800 (PST)",
          "Tue Jan 01 2013 00:00:00 GMT-0800 (PST)",
          "Wed Jan 01 2014 00:00:00 GMT-0800 (PST)",
          "Thu Jan 01 2015 00:00:00 GMT-0800 (PST)",
          "Fri Jan 01 2016 00:00:00 GMT-0800 (PST)",
          "Sun Jan 01 2017 00:00:00 GMT-0800 (PST)",
          "Mon Jan 01 2018 00:00:00 GMT-0800 (PST)",
          "Tue Jan 01 2019 00:00:00 GMT-0800 (PST)",
          "Wed Jan 01 2020 00:00:00 GMT-0800 (PST)",
          "Fri Jan 01 2021 00:00:00 GMT-0800 (PST)",
          "Sat Jan 01 2022 00:00:00 GMT-0800 (PST)",
          "Sun Jan 01 2023 00:00:00 GMT-0800 (PST)",
          "Mon Jan 01 2024 00:00:00 GMT-0800 (PST)",
          "Wed Jan 01 2025 00:00:00 GMT-0800 (PST)",
          "Thu Jan 01 2026 00:00:00 GMT-0800 (PST)",
          "Fri Jan 01 2027 00:00:00 GMT-0800 (PST)",
          "Sat Jan 01 2028 00:00:00 GMT-0800 (PST)",
          "Mon Jan 01 2029 00:00:00 GMT-0800 (PST)",
          "Tue Jan 01 2030 00:00:00 GMT-0800 (PST)",
          "Wed Jan 01 2031 00:00:00 GMT-0800 (PST)",
          "Thu Jan 01 2032 00:00:00 GMT-0800 (PST)",
          "Sat Jan 01 2033 00:00:00 GMT-0800 (PST)",
          "Sun Jan 01 2034 00:00:00 GMT-0800 (PST)",
          "Mon Jan 01 2035 00:00:00 GMT-0800 (PST)",
          "Tue Jan 01 2036 00:00:00 GMT-0800 (PST)",
          "Thu Jan 01 2037 00:00:00 GMT-0800 (PST)",
          "Fri Jan 01 2038 00:00:00 GMT-0800 (PST)",
          "Sat Jan 01 2039 00:00:00 GMT-0800 (PST)",
          "Sun Jan 01 2040 00:00:00 GMT-0800 (PST)",
          "Tue Jan 01 2041 00:00:00 GMT-0800 (PST)",
          "Wed Jan 01 2042 00:00:00 GMT-0800 (PST)",
          "Thu Jan 01 2043 00:00:00 GMT-0800 (PST)",
          "Fri Jan 01 2044 00:00:00 GMT-0800 (PST)",
          "Sun Jan 01 2045 00:00:00 GMT-0800 (PST)",
          "Mon Jan 01 2046 00:00:00 GMT-0800 (PST)",
          "Tue Jan 01 2047 00:00:00 GMT-0800 (PST)",
          "Wed Jan 01 2048 00:00:00 GMT-0800 (PST)",
          "Fri Jan 01 2049 00:00:00 GMT-0800 (PST)"
        ],
        "population": [
          2556505579,
          2593853181,
          2635724824,
          2681048370,
          2729267486,
          2781184998,
          2834435383,
          2890537151,
          2947380005,
          3000023628,
          3042389609,
          3083443346,
          3139645212,
          3209454995,
          3280890090,
          3350151444,
          3420438740,
          3490173281,
          3562227755,
          3637138944,
          3712813618,
          3790668866,
          3867163052,
          3942989103,
          4017615739,
          4090207204,
          4161423905,
          4233413310,
          4305496751,
          4380429849,
          4452686744,
          4535399554,
          4615366900,
          4696410857,
          4776577665,
          4858097523,
          4941825082,
          5028044692,
          5114949044,
          5201502237,
          5288828246,
          5371789734,
          5456405468,
          5538427424,
          5619031095,
          5699913327,
          5779990768,
          5858373016,
          5935741324,
          6012440748,
          6088683554,
          6165323640,
          6241717680,
          6317426395,
          6393120940,
          6469129736,
          6545884439,
          6623571955,
          6700765879,
          6776917465,
          6853019414,
          6929098151,
          7004788328,
          7080175550,
          7155514062,
          7230563690,
          7305219403,
          7379400060,
          7452886652,
          7525539645,
          7597238738,
          7668042575,
          7737974825,
          7806902223,
          7874744182,
          7941443471,
          8007071141,
          8071689859,
          8135259226,
          8197757862,
          8259167105,
          8319554417,
          8378989293,
          8437462573,
          8494958182,
          8551445461,
          8606966383,
          8661571623,
          8715242928,
          8767955464,
          8819679806,
          8870453988,
          8920319273,
          8969241259,
          9017181494,
          9064107637,
          9110049620,
          9155039721,
          9199056831,
          9242083546
        ],
        "deconID": [
          2,
          4,
          6,
          8,
          10,
          12,
          14,
          16,
          18,
          20,
          22,
          24,
          26,
          28,
          30,
          32,
          34,
          36,
          38,
          40,
          42,
          44,
          46,
          48,
          50,
          52,
          54,
          56,
          58,
          60,
          62,
          64,
          66,
          68,
          70,
          72,
          74,
          76,
          78,
          80,
          82,
          84,
          86,
          88,
          90,
          92,
          94,
          96,
          98,
          100,
          102,
          104,
          106,
          108,
          110,
          112,
          114,
          116,
          118,
          120,
          122,
          124,
          126,
          128,
          130,
          132,
          134,
          136,
          138,
          140,
          142,
          144,
          146,
          148,
          150,
          152,
          154,
          156,
          158,
          160,
          162,
          164,
          166,
          168,
          170,
          172,
          174,
          176,
          178,
          180,
          182,
          184,
          186,
          188,
          190,
          192,
          194,
          196,
          198,
          200
        ]
      },
      "attrs": {
        "font-family": [
          "Times",
          "Times",
          "Times",
          "Times",
          "Times",
          "Times",
          "Times",
          "Times",
          "Times",
          "Times",
          "Times",
          "Times",
          "Times",
          "Times",
          "Times",
          "Times",
          "Times",
          "Times",
          "Times",
          "Times",
          "Times",
          "Times",
          "Times",
          "Times",
          "Times",
          "Times",
          "Times",
          "Times",
          "Times",
          "Times",
          "Times",
          "Times",
          "Times",
          "Times",
          "Times",
          "Times",
          "Times",
          "Times",
          "Times",
          "Times",
          "Times",
          "Times",
          "Times",
          "Times",
          "Times",
          "Times",
          "Times",
          "Times",
          "Times",
          "Times",
          "Times",
          "Times",
          "Times",
          "Times",
          "Times",
          "Times",
          "Times",
          "Times",
          "Times",
          "Times",
          "Times",
          "Times",
          "Times",
          "Times",
          "Times",
          "Times",
          "Times",
          "Times",
          "Times",
          "Times",
          "Times",
          "Times",
          "Times",
          "Times",
          "Times",
          "Times",
          "Times",
          "Times",
          "Times",
          "Times",
          "Times",
          "Times",
          "Times",
          "Times",
          "Times",
          "Times",
          "Times",
          "Times",
          "Times",
          "Times",
          "Times",
          "Times",
          "Times",
          "Times",
          "Times",
          "Times",
          "Times",
          "Times",
          "Times",
          "Times"
        ],
        "font-size": [
          "16px",
          "16px",
          "16px",
          "16px",
          "16px",
          "16px",
          "16px",
          "16px",
          "16px",
          "16px",
          "16px",
          "16px",
          "16px",
          "16px",
          "16px",
          "16px",
          "16px",
          "16px",
          "16px",
          "16px",
          "16px",
          "16px",
          "16px",
          "16px",
          "16px",
          "16px",
          "16px",
          "16px",
          "16px",
          "16px",
          "16px",
          "16px",
          "16px",
          "16px",
          "16px",
          "16px",
          "16px",
          "16px",
          "16px",
          "16px",
          "16px",
          "16px",
          "16px",
          "16px",
          "16px",
          "16px",
          "16px",
          "16px",
          "16px",
          "16px",
          "16px",
          "16px",
          "16px",
          "16px",
          "16px",
          "16px",
          "16px",
          "16px",
          "16px",
          "16px",
          "16px",
          "16px",
          "16px",
          "16px",
          "16px",
          "16px",
          "16px",
          "16px",
          "16px",
          "16px",
          "16px",
          "16px",
          "16px",
          "16px",
          "16px",
          "16px",
          "16px",
          "16px",
          "16px",
          "16px",
          "16px",
          "16px",
          "16px",
          "16px",
          "16px",
          "16px",
          "16px",
          "16px",
          "16px",
          "16px",
          "16px",
          "16px",
          "16px",
          "16px",
          "16px",
          "16px",
          "16px",
          "16px",
          "16px",
          "16px"
        ],
        "opacity": [
          1,
          1,
          1,
          1,
          1,
          1,
          1,
          1,
          1,
          1,
          1,
          1,
          1,
          1,
          1,
          1,
          1,
          1,
          1,
          1,
          1,
          1,
          1,
          1,
          1,
          1,
          1,
          1,
          1,
          1,
          1,
          1,
          1,
          1,
          1,
          1,
          1,
          1,
          1,
          1,
          1,
          1,
          1,
          1,
          1,
          1,
          1,
          1,
          1,
          1,
          1,
          1,
          1,
          1,
          1,
          1,
          1,
          1,
          1,
          1,
          1,
          1,
          1,
          1,
          1,
          1,
          1,
          1,
          1,
          1,
          1,
          1,
          1,
          1,
          1,
          1,
          1,
          1,
          1,
          1,
          1,
          1,
          1,
          1,
          1,
          1,
          1,
          1,
          1,
          1,
          1,
          1,
          1,
          1,
          1,
          1,
          1,
          1,
          1,
          1
        ],
        "fill": [
          "rgb(70,130,180)",
          "rgb(70,130,180)",
          "rgb(70,130,180)",
          "rgb(70,130,180)",
          "rgb(70,130,180)",
          "rgb(70,130,180)",
          "rgb(70,130,180)",
          "rgb(70,130,180)",
          "rgb(70,130,180)",
          "rgb(70,130,180)",
          "rgb(70,130,180)",
          "rgb(70,130,180)",
          "rgb(70,130,180)",
          "rgb(70,130,180)",
          "rgb(70,130,180)",
          "rgb(70,130,180)",
          "rgb(70,130,180)",
          "rgb(70,130,180)",
          "rgb(70,130,180)",
          "rgb(70,130,180)",
          "rgb(70,130,180)",
          "rgb(70,130,180)",
          "rgb(70,130,180)",
          "rgb(70,130,180)",
          "rgb(70,130,180)",
          "rgb(70,130,180)",
          "rgb(70,130,180)",
          "rgb(70,130,180)",
          "rgb(70,130,180)",
          "rgb(70,130,180)",
          "rgb(70,130,180)",
          "rgb(70,130,180)",
          "rgb(70,130,180)",
          "rgb(70,130,180)",
          "rgb(70,130,180)",
          "rgb(70,130,180)",
          "rgb(70,130,180)",
          "rgb(70,130,180)",
          "rgb(70,130,180)",
          "rgb(70,130,180)",
          "rgb(70,130,180)",
          "rgb(70,130,180)",
          "rgb(70,130,180)",
          "rgb(70,130,180)",
          "rgb(70,130,180)",
          "rgb(70,130,180)",
          "rgb(70,130,180)",
          "rgb(70,130,180)",
          "rgb(70,130,180)",
          "rgb(70,130,180)",
          "rgb(70,130,180)",
          "rgb(70,130,180)",
          "rgb(70,130,180)",
          "rgb(70,130,180)",
          "rgb(70,130,180)",
          "rgb(70,130,180)",
          "rgb(70,130,180)",
          "rgb(70,130,180)",
          "rgb(70,130,180)",
          "rgb(70,130,180)",
          "rgb(70,130,180)",
          "rgb(70,130,180)",
          "rgb(70,130,180)",
          "rgb(70,130,180)",
          "rgb(70,130,180)",
          "rgb(70,130,180)",
          "rgb(70,130,180)",
          "rgb(70,130,180)",
          "rgb(70,130,180)",
          "rgb(70,130,180)",
          "rgb(70,130,180)",
          "rgb(70,130,180)",
          "rgb(70,130,180)",
          "rgb(70,130,180)",
          "rgb(70,130,180)",
          "rgb(70,130,180)",
          "rgb(70,130,180)",
          "rgb(70,130,180)",
          "rgb(70,130,180)",
          "rgb(70,130,180)",
          "rgb(70,130,180)",
          "rgb(70,130,180)",
          "rgb(70,130,180)",
          "rgb(70,130,180)",
          "rgb(70,130,180)",
          "rgb(70,130,180)",
          "rgb(70,130,180)",
          "rgb(70,130,180)",
          "rgb(70,130,180)",
          "rgb(70,130,180)",
          "rgb(70,130,180)",
          "rgb(70,130,180)",
          "rgb(70,130,180)",
          "rgb(70,130,180)",
          "rgb(70,130,180)",
          "rgb(70,130,180)",
          "rgb(70,130,180)",
          "rgb(70,130,180)",
          "rgb(70,130,180)",
          "rgb(70,130,180)"
        ],
        "fill-opacity": [
          1,
          1,
          1,
          1,
          1,
          1,
          1,
          1,
          1,
          1,
          1,
          1,
          1,
          1,
          1,
          1,
          1,
          1,
          1,
          1,
          1,
          1,
          1,
          1,
          1,
          1,
          1,
          1,
          1,
          1,
          1,
          1,
          1,
          1,
          1,
          1,
          1,
          1,
          1,
          1,
          1,
          1,
          1,
          1,
          1,
          1,
          1,
          1,
          1,
          1,
          1,
          1,
          1,
          1,
          1,
          1,
          1,
          1,
          1,
          1,
          1,
          1,
          1,
          1,
          1,
          1,
          1,
          1,
          1,
          1,
          1,
          1,
          1,
          1,
          1,
          1,
          1,
          1,
          1,
          1,
          1,
          1,
          1,
          1,
          1,
          1,
          1,
          1,
          1,
          1,
          1,
          1,
          1,
          1,
          1,
          1,
          1,
          1,
          1,
          1
        ],
        "stroke": [
          "rgb(255,255,255)",
          "rgb(255,255,255)",
          "rgb(255,255,255)",
          "rgb(255,255,255)",
          "rgb(255,255,255)",
          "rgb(255,255,255)",
          "rgb(255,255,255)",
          "rgb(255,255,255)",
          "rgb(255,255,255)",
          "rgb(255,255,255)",
          "rgb(255,255,255)",
          "rgb(255,255,255)",
          "rgb(255,255,255)",
          "rgb(255,255,255)",
          "rgb(255,255,255)",
          "rgb(255,255,255)",
          "rgb(255,255,255)",
          "rgb(255,255,255)",
          "rgb(255,255,255)",
          "rgb(255,255,255)",
          "rgb(255,255,255)",
          "rgb(255,255,255)",
          "rgb(255,255,255)",
          "rgb(255,255,255)",
          "rgb(255,255,255)",
          "rgb(255,255,255)",
          "rgb(255,255,255)",
          "rgb(255,255,255)",
          "rgb(255,255,255)",
          "rgb(255,255,255)",
          "rgb(255,255,255)",
          "rgb(255,255,255)",
          "rgb(255,255,255)",
          "rgb(255,255,255)",
          "rgb(255,255,255)",
          "rgb(255,255,255)",
          "rgb(255,255,255)",
          "rgb(255,255,255)",
          "rgb(255,255,255)",
          "rgb(255,255,255)",
          "rgb(255,255,255)",
          "rgb(255,255,255)",
          "rgb(255,255,255)",
          "rgb(255,255,255)",
          "rgb(255,255,255)",
          "rgb(255,255,255)",
          "rgb(255,255,255)",
          "rgb(255,255,255)",
          "rgb(255,255,255)",
          "rgb(255,255,255)",
          "rgb(255,255,255)",
          "rgb(255,255,255)",
          "rgb(255,255,255)",
          "rgb(255,255,255)",
          "rgb(255,255,255)",
          "rgb(255,255,255)",
          "rgb(255,255,255)",
          "rgb(255,255,255)",
          "rgb(255,255,255)",
          "rgb(255,255,255)",
          "rgb(255,255,255)",
          "rgb(255,255,255)",
          "rgb(255,255,255)",
          "rgb(255,255,255)",
          "rgb(255,255,255)",
          "rgb(255,255,255)",
          "rgb(255,255,255)",
          "rgb(255,255,255)",
          "rgb(255,255,255)",
          "rgb(255,255,255)",
          "rgb(255,255,255)",
          "rgb(255,255,255)",
          "rgb(255,255,255)",
          "rgb(255,255,255)",
          "rgb(255,255,255)",
          "rgb(255,255,255)",
          "rgb(255,255,255)",
          "rgb(255,255,255)",
          "rgb(255,255,255)",
          "rgb(255,255,255)",
          "rgb(255,255,255)",
          "rgb(255,255,255)",
          "rgb(255,255,255)",
          "rgb(255,255,255)",
          "rgb(255,255,255)",
          "rgb(255,255,255)",
          "rgb(255,255,255)",
          "rgb(255,255,255)",
          "rgb(255,255,255)",
          "rgb(255,255,255)",
          "rgb(255,255,255)",
          "rgb(255,255,255)",
          "rgb(255,255,255)",
          "rgb(255,255,255)",
          "rgb(255,255,255)",
          "rgb(255,255,255)",
          "rgb(255,255,255)",
          "rgb(255,255,255)",
          "rgb(255,255,255)",
          "rgb(255,255,255)"
        ],
        "stroke-width": [
          1,
          1,
          1,
          1,
          1,
          1,
          1,
          1,
          1,
          1,
          1,
          1,
          1,
          1,
          1,
          1,
          1,
          1,
          1,
          1,
          1,
          1,
          1,
          1,
          1,
          1,
          1,
          1,
          1,
          1,
          1,
          1,
          1,
          1,
          1,
          1,
          1,
          1,
          1,
          1,
          1,
          1,
          1,
          1,
          1,
          1,
          1,
          1,
          1,
          1,
          1,
          1,
          1,
          1,
          1,
          1,
          1,
          1,
          1,
          1,
          1,
          1,
          1,
          1,
          1,
          1,
          1,
          1,
          1,
          1,
          1,
          1,
          1,
          1,
          1,
          1,
          1,
          1,
          1,
          1,
          1,
          1,
          1,
          1,
          1,
          1,
          1,
          1,
          1,
          1,
          1,
          1,
          1,
          1,
          1,
          1,
          1,
          1,
          1,
          1
        ],
        "shape": [
          "rect",
          "rect",
          "rect",
          "rect",
          "rect",
          "rect",
          "rect",
          "rect",
          "rect",
          "rect",
          "rect",
          "rect",
          "rect",
          "rect",
          "rect",
          "rect",
          "rect",
          "rect",
          "rect",
          "rect",
          "rect",
          "rect",
          "rect",
          "rect",
          "rect",
          "rect",
          "rect",
          "rect",
          "rect",
          "rect",
          "rect",
          "rect",
          "rect",
          "rect",
          "rect",
          "rect",
          "rect",
          "rect",
          "rect",
          "rect",
          "rect",
          "rect",
          "rect",
          "rect",
          "rect",
          "rect",
          "rect",
          "rect",
          "rect",
          "rect",
          "rect",
          "rect",
          "rect",
          "rect",
          "rect",
          "rect",
          "rect",
          "rect",
          "rect",
          "rect",
          "rect",
          "rect",
          "rect",
          "rect",
          "rect",
          "rect",
          "rect",
          "rect",
          "rect",
          "rect",
          "rect",
          "rect",
          "rect",
          "rect",
          "rect",
          "rect",
          "rect",
          "rect",
          "rect",
          "rect",
          "rect",
          "rect",
          "rect",
          "rect",
          "rect",
          "rect",
          "rect",
          "rect",
          "rect",
          "rect",
          "rect",
          "rect",
          "rect",
          "rect",
          "rect",
          "rect",
          "rect",
          "rect",
          "rect",
          "rect"
        ],
        "xPosition": [
          53.5,
          61.494524002075195,
          69.48904800415039,
          77.50547790527344,
          85.5,
          93.49452209472656,
          101.48904418945312,
          109.50547790527344,
          117.5,
          125.49452209472656,
          133.48904418945312,
          141.50547790527344,
          149.5,
          157.49452209472656,
          165.48904418945312,
          173.50547790527344,
          181.5,
          189.49452209472656,
          197.48904418945312,
          205.50547790527344,
          213.5,
          221.49452209472656,
          229.48904418945312,
          237.50547790527344,
          245.5,
          253.49451446533203,
          261.4890441894531,
          269.5054931640625,
          277.5,
          285.4945068359375,
          293.4890441894531,
          301.5054931640625,
          309.5,
          317.4945373535156,
          325.4890441894531,
          333.5054626464844,
          341.5,
          349.4945373535156,
          357.4890441894531,
          365.5054626464844,
          373.5,
          381.4945373535156,
          389.4890441894531,
          397.5054626464844,
          405.5,
          413.4945373535156,
          421.4890441894531,
          429.5054626464844,
          437.5,
          445.4945373535156,
          453.4890441894531,
          461.5054626464844,
          469.5,
          477.4945373535156,
          485.4890441894531,
          493.5054626464844,
          501.5,
          509.49452209472656,
          517.489013671875,
          525.5054931640625,
          533.5,
          541.4945068359375,
          549.489013671875,
          557.5054931640625,
          565.5,
          573.4945068359375,
          581.4890747070312,
          589.5054931640625,
          597.5,
          605.4945068359375,
          613.4890747070312,
          621.5054931640625,
          629.5,
          637.4945068359375,
          645.4890747070312,
          653.5054931640625,
          661.5,
          669.4945068359375,
          677.4890747070312,
          685.5054931640625,
          693.5,
          701.4945068359375,
          709.4890747070312,
          717.5054931640625,
          725.5,
          733.4945068359375,
          741.4890747070312,
          749.5054931640625,
          757.5,
          765.4945068359375,
          773.4890747070312,
          781.5054931640625,
          789.5,
          797.4945068359375,
          805.4890747070312,
          813.5054931640625,
          821.5,
          829.4945068359375,
          837.4890747070312,
          845.5054931640625
        ],
        "yPosition": [
          395,
          394.5,
          393.5,
          392.5,
          391.5,
          390.5,
          389,
          388,
          386.5,
          385.5,
          384.5,
          384,
          382.5,
          381,
          379.5,
          378,
          376.5,
          375,
          373.5,
          372,
          370,
          368.5,
          367,
          365,
          363.5,
          362,
          360.5,
          359,
          357.5,
          355.5,
          354,
          352.5,
          350.5,
          349,
          347,
          345.5,
          343.5,
          341.5,
          340,
          338,
          336,
          334.5,
          332.5,
          330.5,
          329,
          327,
          325.5,
          323.5,
          322,
          320.5,
          318.5,
          317,
          315.5,
          314,
          312,
          310.5,
          309,
          307,
          305.5,
          304,
          302,
          300.5,
          299,
          297.5,
          295.5,
          294,
          292.5,
          291,
          289,
          287.5,
          286,
          284.5,
          283,
          281.5,
          280,
          278.5,
          277,
          276,
          274.5,
          273,
          272,
          270.5,
          269,
          268,
          266.5,
          265.5,
          264,
          263,
          262,
          261,
          259.5,
          258.5,
          257.5,
          256.5,
          255.5,
          254.5,
          253.5,
          252.5,
          251.5,
          250.5
        ],
        "area": [
          888,
          895.9995727539062,
          911.9991302490234,
          928,
          944,
          960,
          984,
          1000,
          1024,
          1040,
          1056,
          1064,
          1088,
          1112,
          1136,
          1160,
          1184,
          1208,
          1232,
          1256,
          1288,
          1312,
          1336,
          1368,
          1392,
          1415.997299194336,
          1440,
          1464,
          1488,
          1520,
          1544,
          1568,
          1600,
          1624,
          1656,
          1680,
          1712,
          1744,
          1768,
          1800,
          1832,
          1856,
          1888,
          1920,
          1944,
          1976,
          2000,
          2032,
          2056,
          2080,
          2112,
          2136,
          2160,
          2184,
          2216,
          2240,
          2264,
          2295.991241455078,
          2320,
          2344,
          2376,
          2400,
          2424,
          2448,
          2480,
          2504,
          2528,
          2552,
          2584,
          2608,
          2632,
          2656,
          2680,
          2704,
          2728,
          2752,
          2776,
          2792,
          2816,
          2840,
          2856,
          2880,
          2904,
          2920,
          2944,
          2960,
          2984,
          3000,
          3016,
          3032,
          3056,
          3072,
          3088,
          3104,
          3120,
          3136,
          3152,
          3168,
          3184,
          3200
        ],
        "width": [
          8,
          7.999996185302734,
          7.999992370605469,
          8,
          8,
          8,
          8,
          8,
          8,
          8,
          8,
          8,
          8,
          8,
          8,
          8,
          8,
          8,
          8,
          8,
          8,
          8,
          8,
          8,
          8,
          7.9999847412109375,
          8,
          8,
          8,
          8,
          8,
          8,
          8,
          8,
          8,
          8,
          8,
          8,
          8,
          8,
          8,
          8,
          8,
          8,
          8,
          8,
          8,
          8,
          8,
          8,
          8,
          8,
          8,
          8,
          8,
          8,
          8,
          7.999969482421875,
          8,
          8,
          8,
          8,
          8,
          8,
          8,
          8,
          8,
          8,
          8,
          8,
          8,
          8,
          8,
          8,
          8,
          8,
          8,
          8,
          8,
          8,
          8,
          8,
          8,
          8,
          8,
          8,
          8,
          8,
          8,
          8,
          8,
          8,
          8,
          8,
          8,
          8,
          8,
          8,
          8,
          8
        ],
        "height": [
          111,
          112,
          114,
          116,
          118,
          120,
          123,
          125,
          128,
          130,
          132,
          133,
          136,
          139,
          142,
          145,
          148,
          151,
          154,
          157,
          161,
          164,
          167,
          171,
          174,
          177,
          180,
          183,
          186,
          190,
          193,
          196,
          200,
          203,
          207,
          210,
          214,
          218,
          221,
          225,
          229,
          232,
          236,
          240,
          243,
          247,
          250,
          254,
          257,
          260,
          264,
          267,
          270,
          273,
          277,
          280,
          283,
          287,
          290,
          293,
          297,
          300,
          303,
          306,
          310,
          313,
          316,
          319,
          323,
          326,
          329,
          332,
          335,
          338,
          341,
          344,
          347,
          349,
          352,
          355,
          357,
          360,
          363,
          365,
          368,
          370,
          373,
          375,
          377,
          379,
          382,
          384,
          386,
          388,
          390,
          392,
          394,
          396,
          398,
          400
        ],
        "rotation": [
          0,
          0,
          0,
          0,
          0,
          0,
          0,
          0,
          0,
          0,
          0,
          0,
          0,
          0,
          0,
          0,
          0,
          0,
          0,
          0,
          0,
          0,
          0,
          0,
          0,
          0,
          0,
          0,
          0,
          0,
          0,
          0,
          0,
          0,
          0,
          0,
          0,
          0,
          0,
          0,
          0,
          0,
          0,
          0,
          0,
          0,
          0,
          0,
          0,
          0,
          0,
          0,
          0,
          0,
          0,
          0,
          0,
          0,
          0,
          0,
          0,
          0,
          0,
          0,
          0,
          0,
          0,
          0,
          0,
          0,
          0,
          0,
          0,
          0,
          0,
          0,
          0,
          0,
          0,
          0,
          0,
          0,
          0,
          0,
          0,
          0,
          0,
          0,
          0,
          0,
          0,
          0,
          0,
          0,
          0,
          0,
          0,
          0,
          0,
          0
        ]
      },
      "nodeAttrs": [
        {
          "x": "-0.5",
          "y": "289.5",
          "width": "8",
          "height": "111",
          "text": ""
        },
        {
          "x": "7.494524298425736",
          "y": "288.5",
          "width": "8",
          "height": "112",
          "text": ""
        },
        {
          "x": "15.489048596851472",
          "y": "286.5",
          "width": "8",
          "height": "114",
          "text": ""
        },
        {
          "x": "23.505475701574262",
          "y": "284.5",
          "width": "8",
          "height": "116",
          "text": ""
        },
        {
          "x": "31.5",
          "y": "282.5",
          "width": "8",
          "height": "118",
          "text": ""
        },
        {
          "x": "39.49452429842574",
          "y": "280.5",
          "width": "8",
          "height": "120",
          "text": ""
        },
        {
          "x": "47.48904859685147",
          "y": "277.5",
          "width": "8",
          "height": "123",
          "text": ""
        },
        {
          "x": "55.505475701574255",
          "y": "275.5",
          "width": "8",
          "height": "125",
          "text": ""
        },
        {
          "x": "63.5",
          "y": "272.5",
          "width": "8",
          "height": "128",
          "text": ""
        },
        {
          "x": "71.49452429842573",
          "y": "270.5",
          "width": "8",
          "height": "130",
          "text": ""
        },
        {
          "x": "79.48904859685148",
          "y": "268.5",
          "width": "8",
          "height": "132",
          "text": ""
        },
        {
          "x": "87.50547570157427",
          "y": "267.5",
          "width": "8",
          "height": "133",
          "text": ""
        },
        {
          "x": "95.5",
          "y": "264.5",
          "width": "8",
          "height": "136",
          "text": ""
        },
        {
          "x": "103.49452429842573",
          "y": "261.5",
          "width": "8",
          "height": "139",
          "text": ""
        },
        {
          "x": "111.48904859685148",
          "y": "258.5",
          "width": "8",
          "height": "142",
          "text": ""
        },
        {
          "x": "119.50547570157427",
          "y": "255.5",
          "width": "8",
          "height": "145",
          "text": ""
        },
        {
          "x": "127.5",
          "y": "252.5",
          "width": "8",
          "height": "148",
          "text": ""
        },
        {
          "x": "135.49452429842574",
          "y": "249.5",
          "width": "8",
          "height": "151",
          "text": ""
        },
        {
          "x": "143.48904859685146",
          "y": "246.5",
          "width": "8",
          "height": "154",
          "text": ""
        },
        {
          "x": "151.50547570157426",
          "y": "243.5",
          "width": "8",
          "height": "157",
          "text": ""
        },
        {
          "x": "159.5",
          "y": "239.5",
          "width": "8",
          "height": "161",
          "text": ""
        },
        {
          "x": "167.49452429842574",
          "y": "236.5",
          "width": "8",
          "height": "164",
          "text": ""
        },
        {
          "x": "175.48904859685146",
          "y": "233.5",
          "width": "8",
          "height": "167",
          "text": ""
        },
        {
          "x": "183.50547570157426",
          "y": "229.5",
          "width": "8",
          "height": "171",
          "text": ""
        },
        {
          "x": "191.5",
          "y": "226.5",
          "width": "8",
          "height": "174",
          "text": ""
        },
        {
          "x": "199.49452429842574",
          "y": "223.5",
          "width": "8",
          "height": "177",
          "text": ""
        },
        {
          "x": "207.48904859685146",
          "y": "220.5",
          "width": "8",
          "height": "180",
          "text": ""
        },
        {
          "x": "215.50547570157426",
          "y": "217.5",
          "width": "8",
          "height": "183",
          "text": ""
        },
        {
          "x": "223.50000000000003",
          "y": "214.5",
          "width": "8",
          "height": "186",
          "text": ""
        },
        {
          "x": "231.49452429842574",
          "y": "210.5",
          "width": "8",
          "height": "190",
          "text": ""
        },
        {
          "x": "239.4890485968515",
          "y": "207.5",
          "width": "8",
          "height": "193",
          "text": ""
        },
        {
          "x": "247.50547570157426",
          "y": "204.5",
          "width": "8",
          "height": "196",
          "text": ""
        },
        {
          "x": "255.5",
          "y": "200.5",
          "width": "8",
          "height": "200",
          "text": ""
        },
        {
          "x": "263.4945242984257",
          "y": "197.5",
          "width": "8",
          "height": "203",
          "text": ""
        },
        {
          "x": "271.4890485968515",
          "y": "193.5",
          "width": "8",
          "height": "207",
          "text": ""
        },
        {
          "x": "279.50547570157426",
          "y": "190.5",
          "width": "8",
          "height": "210",
          "text": ""
        },
        {
          "x": "287.5",
          "y": "186.5",
          "width": "8",
          "height": "214",
          "text": ""
        },
        {
          "x": "295.49452429842574",
          "y": "182.5",
          "width": "8",
          "height": "218",
          "text": ""
        },
        {
          "x": "303.48904859685143",
          "y": "179.5",
          "width": "8",
          "height": "221",
          "text": ""
        },
        {
          "x": "311.50547570157426",
          "y": "175.5",
          "width": "8",
          "height": "225",
          "text": ""
        },
        {
          "x": "319.5",
          "y": "171.5",
          "width": "8",
          "height": "229",
          "text": ""
        },
        {
          "x": "327.49452429842574",
          "y": "168.5",
          "width": "8",
          "height": "232",
          "text": ""
        },
        {
          "x": "335.4890485968515",
          "y": "164.5",
          "width": "8",
          "height": "236",
          "text": ""
        },
        {
          "x": "343.50547570157426",
          "y": "160.5",
          "width": "8",
          "height": "240",
          "text": ""
        },
        {
          "x": "351.5",
          "y": "157.5",
          "width": "8",
          "height": "243",
          "text": ""
        },
        {
          "x": "359.49452429842574",
          "y": "153.5",
          "width": "8",
          "height": "247",
          "text": ""
        },
        {
          "x": "367.4890485968515",
          "y": "150.5",
          "width": "8",
          "height": "250",
          "text": ""
        },
        {
          "x": "375.50547570157426",
          "y": "146.5",
          "width": "8",
          "height": "254",
          "text": ""
        },
        {
          "x": "383.5",
          "y": "143.5",
          "width": "8",
          "height": "257",
          "text": ""
        },
        {
          "x": "391.49452429842574",
          "y": "140.5",
          "width": "8",
          "height": "260",
          "text": ""
        },
        {
          "x": "399.4890485968515",
          "y": "136.5",
          "width": "8",
          "height": "264",
          "text": ""
        },
        {
          "x": "407.5054757015743",
          "y": "133.5",
          "width": "8",
          "height": "267",
          "text": ""
        },
        {
          "x": "415.5",
          "y": "130.5",
          "width": "8",
          "height": "270",
          "text": ""
        },
        {
          "x": "423.49452429842574",
          "y": "127.5",
          "width": "8",
          "height": "273",
          "text": ""
        },
        {
          "x": "431.48904859685143",
          "y": "123.5",
          "width": "8",
          "height": "277",
          "text": ""
        },
        {
          "x": "439.50547570157426",
          "y": "120.5",
          "width": "8",
          "height": "280",
          "text": ""
        },
        {
          "x": "447.50000000000006",
          "y": "117.5",
          "width": "8",
          "height": "283",
          "text": ""
        },
        {
          "x": "455.49452429842574",
          "y": "113.5",
          "width": "8",
          "height": "287",
          "text": ""
        },
        {
          "x": "463.4890485968515",
          "y": "110.5",
          "width": "8",
          "height": "290",
          "text": ""
        },
        {
          "x": "471.50547570157426",
          "y": "107.5",
          "width": "8",
          "height": "293",
          "text": ""
        },
        {
          "x": "479.5",
          "y": "103.5",
          "width": "8",
          "height": "297",
          "text": ""
        },
        {
          "x": "487.4945242984257",
          "y": "100.5",
          "width": "8",
          "height": "300",
          "text": ""
        },
        {
          "x": "495.4890485968515",
          "y": "97.5",
          "width": "8",
          "height": "303",
          "text": ""
        },
        {
          "x": "503.5054757015743",
          "y": "94.5",
          "width": "8",
          "height": "306",
          "text": ""
        },
        {
          "x": "511.5",
          "y": "90.5",
          "width": "8",
          "height": "310",
          "text": ""
        },
        {
          "x": "519.4945242984257",
          "y": "87.5",
          "width": "8",
          "height": "313",
          "text": ""
        },
        {
          "x": "527.4890485968514",
          "y": "84.5",
          "width": "8",
          "height": "316",
          "text": ""
        },
        {
          "x": "535.5054757015743",
          "y": "81.5",
          "width": "8",
          "height": "319",
          "text": ""
        },
        {
          "x": "543.5",
          "y": "77.5",
          "width": "8",
          "height": "323",
          "text": ""
        },
        {
          "x": "551.4945242984257",
          "y": "74.5",
          "width": "8",
          "height": "326",
          "text": ""
        },
        {
          "x": "559.4890485968515",
          "y": "71.5",
          "width": "8",
          "height": "329",
          "text": ""
        },
        {
          "x": "567.5054757015743",
          "y": "68.5",
          "width": "8",
          "height": "332",
          "text": ""
        },
        {
          "x": "575.5",
          "y": "65.5",
          "width": "8",
          "height": "335",
          "text": ""
        },
        {
          "x": "583.4945242984257",
          "y": "62.5",
          "width": "8",
          "height": "338",
          "text": ""
        },
        {
          "x": "591.4890485968515",
          "y": "59.5",
          "width": "8",
          "height": "341",
          "text": ""
        },
        {
          "x": "599.5054757015743",
          "y": "56.5",
          "width": "8",
          "height": "344",
          "text": ""
        },
        {
          "x": "607.5",
          "y": "53.5",
          "width": "8",
          "height": "347",
          "text": ""
        },
        {
          "x": "615.4945242984257",
          "y": "51.5",
          "width": "8",
          "height": "349",
          "text": ""
        },
        {
          "x": "623.4890485968515",
          "y": "48.5",
          "width": "8",
          "height": "352",
          "text": ""
        },
        {
          "x": "631.5054757015743",
          "y": "45.5",
          "width": "8",
          "height": "355",
          "text": ""
        },
        {
          "x": "639.5",
          "y": "43.5",
          "width": "8",
          "height": "357",
          "text": ""
        },
        {
          "x": "647.4945242984257",
          "y": "40.5",
          "width": "8",
          "height": "360",
          "text": ""
        },
        {
          "x": "655.4890485968515",
          "y": "37.5",
          "width": "8",
          "height": "363",
          "text": ""
        },
        {
          "x": "663.5054757015743",
          "y": "35.5",
          "width": "8",
          "height": "365",
          "text": ""
        },
        {
          "x": "671.5",
          "y": "32.5",
          "width": "8",
          "height": "368",
          "text": ""
        },
        {
          "x": "679.4945242984257",
          "y": "30.5",
          "width": "8",
          "height": "370",
          "text": ""
        },
        {
          "x": "687.4890485968515",
          "y": "27.5",
          "width": "8",
          "height": "373",
          "text": ""
        },
        {
          "x": "695.5054757015743",
          "y": "25.5",
          "width": "8",
          "height": "375",
          "text": ""
        },
        {
          "x": "703.5",
          "y": "23.5",
          "width": "8",
          "height": "377",
          "text": ""
        },
        {
          "x": "711.4945242984257",
          "y": "21.5",
          "width": "8",
          "height": "379",
          "text": ""
        },
        {
          "x": "719.4890485968515",
          "y": "18.5",
          "width": "8",
          "height": "382",
          "text": ""
        },
        {
          "x": "727.5054757015743",
          "y": "16.5",
          "width": "8",
          "height": "384",
          "text": ""
        },
        {
          "x": "735.5",
          "y": "14.5",
          "width": "8",
          "height": "386",
          "text": ""
        },
        {
          "x": "743.4945242984257",
          "y": "12.5",
          "width": "8",
          "height": "388",
          "text": ""
        },
        {
          "x": "751.4890485968515",
          "y": "10.5",
          "width": "8",
          "height": "390",
          "text": ""
        },
        {
          "x": "759.5054757015743",
          "y": "8.5",
          "width": "8",
          "height": "392",
          "text": ""
        },
        {
          "x": "767.5",
          "y": "6.5",
          "width": "8",
          "height": "394",
          "text": ""
        },
        {
          "x": "775.4945242984257",
          "y": "4.5",
          "width": "8",
          "height": "396",
          "text": ""
        },
        {
          "x": "783.4890485968515",
          "y": "2.5",
          "width": "8",
          "height": "398",
          "text": ""
        },
        {
          "x": "791.5054757015743",
          "y": "0.5",
          "width": "8",
          "height": "400",
          "text": ""
        }
      ],
      "mappings": [
        {
          "type": "linear",
          "data": ["deconID"],
          "attr": "xPosition",
          "params": {
            "attrMin": 53.49717727132359,
            "coeffs": [
              4.000000870690632,
              45.497175529942325
            ],
            "err": 0.9999999992969311
          }
        },
        {
          "type": "linear",
          "data": ["population"],
          "attr": "yPosition",
          "params": {
            "attrMin": 395.1717644980322,
            "coeffs": [
              -2.1638970548825833e-8,
              450.49191342992214
            ],
            "err": 0.9999911848124404
          }
        },
        {
          "type": "linear",
          "data": ["population"],
          "attr": "area",
          "params": {
            "attrMin": 885.2516118978821,
            "coeffs": [
              3.4622353715128147e-7,
              0.12920758951727862
            ],
            "err": 0.9999911855999527
          }
        },
        {
          "type": "linear",
          "data": ["population"],
          "attr": "height",
          "params": {
            "attrMin": 110.65647100393501,
            "coeffs": [
              4.327794109765163e-8,
              0.01617314015523519
            ],
            "err": 0.9999911848124404
          }
        }
      ]
    },
    {
      "schema": ["deconID"],
      "nodeType": "line",
      "ids": [
        204,
        207,
        210,
        213,
        216,
        219,
        222,
        225,
        228,
        231,
        234,
        237,
        240,
        243,
        246,
        249,
        252,
        255,
        258,
        261,
        264
      ],
      "data": {
        "deconID": [
          204,
          207,
          210,
          213,
          216,
          219,
          222,
          225,
          228,
          231,
          234,
          237,
          240,
          243,
          246,
          249,
          252,
          255,
          258,
          261,
          264
        ]
      },
      "attrs": {
        "font-family": [
          "Times",
          "Times",
          "Times",
          "Times",
          "Times",
          "Times",
          "Times",
          "Times",
          "Times",
          "Times",
          "Times",
          "Times",
          "Times",
          "Times",
          "Times",
          "Times",
          "Times",
          "Times",
          "Times",
          "Times",
          "Times"
        ],
        "font-size": [
          "16px",
          "16px",
          "16px",
          "16px",
          "16px",
          "16px",
          "16px",
          "16px",
          "16px",
          "16px",
          "16px",
          "16px",
          "16px",
          "16px",
          "16px",
          "16px",
          "16px",
          "16px",
          "16px",
          "16px",
          "16px"
        ],
        "opacity": [
          1,
          1,
          1,
          1,
          1,
          1,
          1,
          1,
          1,
          1,
          1,
          1,
          1,
          1,
          1,
          1,
          1,
          1,
          1,
          1,
          1
        ],
        "fill": [
          "rgb(0,0,0)",
          "rgb(0,0,0)",
          "rgb(0,0,0)",
          "rgb(0,0,0)",
          "rgb(0,0,0)",
          "rgb(0,0,0)",
          "rgb(0,0,0)",
          "rgb(0,0,0)",
          "rgb(0,0,0)",
          "rgb(0,0,0)",
          "rgb(0,0,0)",
          "rgb(0,0,0)",
          "rgb(0,0,0)",
          "rgb(0,0,0)",
          "rgb(0,0,0)",
          "rgb(0,0,0)",
          "rgb(0,0,0)",
          "rgb(0,0,0)",
          "rgb(0,0,0)",
          "rgb(0,0,0)",
          "rgb(0,0,0)"
        ],
        "fill-opacity": [
          1,
          1,
          1,
          1,
          1,
          1,
          1,
          1,
          1,
          1,
          1,
          1,
          1,
          1,
          1,
          1,
          1,
          1,
          1,
          1,
          1
        ],
        "stroke": [
          "rgb(0,0,0)",
          "rgb(0,0,0)",
          "rgb(0,0,0)",
          "rgb(0,0,0)",
          "rgb(0,0,0)",
          "rgb(0,0,0)",
          "rgb(0,0,0)",
          "rgb(0,0,0)",
          "rgb(0,0,0)",
          "rgb(0,0,0)",
          "rgb(0,0,0)",
          "rgb(0,0,0)",
          "rgb(0,0,0)",
          "rgb(0,0,0)",
          "rgb(0,0,0)",
          "rgb(0,0,0)",
          "rgb(0,0,0)",
          "rgb(0,0,0)",
          "rgb(0,0,0)",
          "rgb(0,0,0)",
          "rgb(0,0,0)"
        ],
        "stroke-width": [
          1,
          1,
          1,
          1,
          1,
          1,
          1,
          1,
          1,
          1,
          1,
          1,
          1,
          1,
          1,
          1,
          1,
          1,
          1,
          1,
          1
        ],
        "shape": [
          "line",
          "line",
          "line",
          "line",
          "line",
          "line",
          "line",
          "line",
          "line",
          "line",
          "line",
          "line",
          "line",
          "line",
          "line",
          "line",
          "line",
          "line",
          "line",
          "line",
          "line"
        ],
        "xPosition": [
          50,
          89.99452209472656,
          129.98904418945312,
          170.00547790527344,
          210,
          249.99452209472656,
          289.9890441894531,
          330.0054626464844,
          370,
          409.9945373535156,
          449.9890441894531,
          490.0054626464844,
          530,
          569.9945068359375,
          609.9890747070312,
          650.0054931640625,
          690,
          729.9945068359375,
          769.9890747070312,
          810.0054931640625,
          850
        ],
        "yPosition": [
          453,
          453,
          453,
          453,
          453,
          453,
          453,
          453,
          453,
          453,
          453,
          453,
          453,
          453,
          453,
          453,
          453,
          453,
          453,
          453,
          453
        ],
        "area": [
          0,
          0,
          0,
          0,
          0,
          0,
          0,
          0,
          0,
          0,
          0,
          0,
          0,
          0,
          0,
          0,
          0,
          0,
          0,
          0,
          0
        ],
        "width": [
          0,
          0,
          0,
          0,
          0,
          0,
          0,
          0,
          0,
          0,
          0,
          0,
          0,
          0,
          0,
          0,
          0,
          0,
          0,
          0,
          0
        ],
        "height": [
          6,
          6,
          6,
          6,
          6,
          6,
          6,
          6,
          6,
          6,
          6,
          6,
          6,
          6,
          6,
          6,
          6,
          6,
          6,
          6,
          6
        ],
        "rotation": [
          0,
          0,
          0,
          0,
          0,
          0,
          0,
          0,
          0,
          0,
          0,
          0,
          0,
          0,
          0,
          0,
          0,
          0,
          0,
          0,
          0
        ]
      },
      "nodeAttrs": [
        {
          "y2": "6",
          "x2": "0",
          "text": ""
        },
        {
          "y2": "6",
          "x2": "0",
          "text": ""
        },
        {
          "y2": "6",
          "x2": "0",
          "text": ""
        },
        {
          "y2": "6",
          "x2": "0",
          "text": ""
        },
        {
          "y2": "6",
          "x2": "0",
          "text": ""
        },
        {
          "y2": "6",
          "x2": "0",
          "text": ""
        },
        {
          "y2": "6",
          "x2": "0",
          "text": ""
        },
        {
          "y2": "6",
          "x2": "0",
          "text": ""
        },
        {
          "y2": "6",
          "x2": "0",
          "text": ""
        },
        {
          "y2": "6",
          "x2": "0",
          "text": ""
        },
        {
          "y2": "6",
          "x2": "0",
          "text": ""
        },
        {
          "y2": "6",
          "x2": "0",
          "text": ""
        },
        {
          "y2": "6",
          "x2": "0",
          "text": ""
        },
        {
          "y2": "6",
          "x2": "0",
          "text": ""
        },
        {
          "y2": "6",
          "x2": "0",
          "text": ""
        },
        {
          "y2": "6",
          "x2": "0",
          "text": ""
        },
        {
          "y2": "6",
          "x2": "0",
          "text": ""
        },
        {
          "y2": "6",
          "x2": "0",
          "text": ""
        },
        {
          "y2": "6",
          "x2": "0",
          "text": ""
        },
        {
          "y2": "6",
          "x2": "0",
          "text": ""
        },
        {
          "y2": "6",
          "x2": "0",
          "text": ""
        }
      ],
      "axis": "xaxis",
      "name": "xaxis-ticks",
      "mappings": [
        {
          "type": "linear",
          "data": ["deconID"],
          "attr": "xPosition",
          "params": {
            "attrMin": 49.996676490424306,
            "coeffs": [
              13.333357238769558,
              -2670.0082002185654
            ],
            "err": 0.9999999993892534
          }
        }
      ]
    },
    {
      "schema": ["deconID"],
      "nodeType": "text",
      "ids": [
        205,
        208,
        211,
        214,
        217,
        220,
        223,
        226,
        229,
        232,
        235,
        238,
        241,
        244,
        247,
        250,
        253,
        256,
        259,
        262,
        265
      ],
      "data": {
        "deconID": [
          205,
          208,
          211,
          214,
          217,
          220,
          223,
          226,
          229,
          232,
          235,
          238,
          241,
          244,
          247,
          250,
          253,
          256,
          259,
          262,
          265
        ]
      },
      "attrs": {
        "font-family": [
          "Times",
          "Times",
          "Times",
          "Times",
          "Times",
          "Times",
          "Times",
          "Times",
          "Times",
          "Times",
          "Times",
          "Times",
          "Times",
          "Times",
          "Times",
          "Times",
          "Times",
          "Times",
          "Times",
          "Times",
          "Times"
        ],
        "font-size": [
          "12px",
          "12px",
          "12px",
          "12px",
          "12px",
          "12px",
          "12px",
          "12px",
          "12px",
          "12px",
          "12px",
          "12px",
          "12px",
          "12px",
          "12px",
          "12px",
          "12px",
          "12px",
          "12px",
          "12px",
          "12px"
        ],
        "opacity": [
          1,
          1,
          1,
          1,
          1,
          1,
          1,
          1,
          1,
          1,
          1,
          1,
          1,
          1,
          1,
          1,
          1,
          1,
          1,
          1,
          1
        ],
        "fill": [
          "rgb(0,0,0)",
          "rgb(0,0,0)",
          "rgb(0,0,0)",
          "rgb(0,0,0)",
          "rgb(0,0,0)",
          "rgb(0,0,0)",
          "rgb(0,0,0)",
          "rgb(0,0,0)",
          "rgb(0,0,0)",
          "rgb(0,0,0)",
          "rgb(0,0,0)",
          "rgb(0,0,0)",
          "rgb(0,0,0)",
          "rgb(0,0,0)",
          "rgb(0,0,0)",
          "rgb(0,0,0)",
          "rgb(0,0,0)",
          "rgb(0,0,0)",
          "rgb(0,0,0)",
          "rgb(0,0,0)",
          "rgb(0,0,0)"
        ],
        "fill-opacity": [
          1,
          1,
          1,
          1,
          1,
          1,
          1,
          1,
          1,
          1,
          1,
          1,
          1,
          1,
          1,
          1,
          1,
          1,
          1,
          1,
          1
        ],
        "stroke": [
          "none",
          "none",
          "none",
          "none",
          "none",
          "none",
          "none",
          "none",
          "none",
          "none",
          "none",
          "none",
          "none",
          "none",
          "none",
          "none",
          "none",
          "none",
          "none",
          "none",
          "none"
        ],
        "stroke-width": [
          1,
          1,
          1,
          1,
          1,
          1,
          1,
          1,
          1,
          1,
          1,
          1,
          1,
          1,
          1,
          1,
          1,
          1,
          1,
          1,
          1
        ],
        "shape": [
          "text",
          "text",
          "text",
          "text",
          "text",
          "text",
          "text",
          "text",
          "text",
          "text",
          "text",
          "text",
          "text",
          "text",
          "text",
          "text",
          "text",
          "text",
          "text",
          "text",
          "text"
        ],
        "xPosition": [
          50,
          89.99452209472656,
          129.9890480041504,
          170.00547790527344,
          210,
          249.99451446533203,
          289.9890441894531,
          330.0054626464844,
          370,
          409.9945373535156,
          449.9890441894531,
          490.0054626464844,
          530,
          569.9945068359375,
          609.9890747070312,
          650.0054931640625,
          690,
          729.9945068359375,
          769.9890747070312,
          810.0054931640625,
          850
        ],
        "yPosition": [
          464.5234375,
          464.5234375,
          464.5234375,
          464.5234375,
          464.5234375,
          464.5234375,
          464.5234375,
          464.5234375,
          464.5234375,
          464.5234375,
          464.5234375,
          464.5234375,
          464.5234375,
          464.5234375,
          464.5234375,
          464.5234375,
          464.5234375,
          464.5234375,
          464.5234375,
          464.5234375,
          464.5234375
        ],
        "area": [
          288.375,
          288.375,
          288.37490832805634,
          288.375,
          288.375,
          288.37481665611267,
          288.375,
          288.375,
          288.375,
          288.375,
          288.375,
          288.375,
          288.375,
          288.375,
          288.375,
          288.375,
          288.375,
          288.375,
          288.375,
          288.375,
          288.375
        ],
        "width": [
          24,
          24,
          23.99999237060547,
          24,
          24,
          23.999984741210938,
          24,
          24,
          24,
          24,
          24,
          24,
          24,
          24,
          24,
          24,
          24,
          24,
          24,
          24,
          24
        ],
        "height": [
          12.015625,
          12.015625,
          12.015625,
          12.015625,
          12.015625,
          12.015625,
          12.015625,
          12.015625,
          12.015625,
          12.015625,
          12.015625,
          12.015625,
          12.015625,
          12.015625,
          12.015625,
          12.015625,
          12.015625,
          12.015625,
          12.015625,
          12.015625,
          12.015625
        ],
        "rotation": [
          0,
          0,
          0,
          0,
          0,
          0,
          0,
          0,
          0,
          0,
          0,
          0,
          0,
          0,
          0,
          0,
          0,
          0,
          0,
          0,
          0
        ]
      },
      "nodeAttrs": [
        {
          "dy": ".71em",
          "y": "9",
          "x": "0",
          "style": "text-anchor: middle;",
          "text": "1950"
        },
        {
          "dy": ".71em",
          "y": "9",
          "x": "0",
          "style": "text-anchor: middle;",
          "text": "1955"
        },
        {
          "dy": ".71em",
          "y": "9",
          "x": "0",
          "style": "text-anchor: middle;",
          "text": "1960"
        },
        {
          "dy": ".71em",
          "y": "9",
          "x": "0",
          "style": "text-anchor: middle;",
          "text": "1965"
        },
        {
          "dy": ".71em",
          "y": "9",
          "x": "0",
          "style": "text-anchor: middle;",
          "text": "1970"
        },
        {
          "dy": ".71em",
          "y": "9",
          "x": "0",
          "style": "text-anchor: middle;",
          "text": "1975"
        },
        {
          "dy": ".71em",
          "y": "9",
          "x": "0",
          "style": "text-anchor: middle;",
          "text": "1980"
        },
        {
          "dy": ".71em",
          "y": "9",
          "x": "0",
          "style": "text-anchor: middle;",
          "text": "1985"
        },
        {
          "dy": ".71em",
          "y": "9",
          "x": "0",
          "style": "text-anchor: middle;",
          "text": "1990"
        },
        {
          "dy": ".71em",
          "y": "9",
          "x": "0",
          "style": "text-anchor: middle;",
          "text": "1995"
        },
        {
          "dy": ".71em",
          "y": "9",
          "x": "0",
          "style": "text-anchor: middle;",
          "text": "2000"
        },
        {
          "dy": ".71em",
          "y": "9",
          "x": "0",
          "style": "text-anchor: middle;",
          "text": "2005"
        },
        {
          "dy": ".71em",
          "y": "9",
          "x": "0",
          "style": "text-anchor: middle;",
          "text": "2010"
        },
        {
          "dy": ".71em",
          "y": "9",
          "x": "0",
          "style": "text-anchor: middle;",
          "text": "2015"
        },
        {
          "dy": ".71em",
          "y": "9",
          "x": "0",
          "style": "text-anchor: middle;",
          "text": "2020"
        },
        {
          "dy": ".71em",
          "y": "9",
          "x": "0",
          "style": "text-anchor: middle;",
          "text": "2025"
        },
        {
          "dy": ".71em",
          "y": "9",
          "x": "0",
          "style": "text-anchor: middle;",
          "text": "2030"
        },
        {
          "dy": ".71em",
          "y": "9",
          "x": "0",
          "style": "text-anchor: middle;",
          "text": "2035"
        },
        {
          "dy": ".71em",
          "y": "9",
          "x": "0",
          "style": "text-anchor: middle;",
          "text": "2040"
        },
        {
          "dy": ".71em",
          "y": "9",
          "x": "0",
          "style": "text-anchor: middle;",
          "text": "2045"
        },
        {
          "dy": ".71em",
          "y": "9",
          "x": "0",
          "style": "text-anchor: middle;",
          "text": "2050"
        }
      ],
      "axis": "xaxis",
      "name": "xaxis-labels",
      "mappings": [
        {
          "type": "linear",
          "data": ["deconID"],
          "attr": "xPosition",
          "params": {
            "attrMin": 49.996676209675115,
            "coeffs": [
              13.333357242072289,
              -2683.341558415144
            ],
            "err": 0.9999999993892704
          }
        }
      ]
    },
    {
      "schema": [
        "number",
        "deconID"
      ],
      "nodeType": "line",
      "ids": [
        269,
        272,
        275,
        278,
        281,
        284,
        287,
        290,
        293,
        296
      ],
      "data": {
        "number": [
          0,
          1000000000,
          2000000000,
          3000000000,
          4000000000,
          5000000000,
          6000000000,
          7000000000,
          8000000000,
          9000000000
        ],
        "deconID": [
          269,
          272,
          275,
          278,
          281,
          284,
          287,
          290,
          293,
          296
        ]
      },
      "attrs": {
        "font-family": [
          "Times",
          "Times",
          "Times",
          "Times",
          "Times",
          "Times",
          "Times",
          "Times",
          "Times",
          "Times"
        ],
        "font-size": [
          "16px",
          "16px",
          "16px",
          "16px",
          "16px",
          "16px",
          "16px",
          "16px",
          "16px",
          "16px"
        ],
        "opacity": [
          1,
          1,
          1,
          1,
          1,
          1,
          1,
          1,
          1,
          1
        ],
        "fill": [
          "rgb(0,0,0)",
          "rgb(0,0,0)",
          "rgb(0,0,0)",
          "rgb(0,0,0)",
          "rgb(0,0,0)",
          "rgb(0,0,0)",
          "rgb(0,0,0)",
          "rgb(0,0,0)",
          "rgb(0,0,0)",
          "rgb(0,0,0)"
        ],
        "fill-opacity": [
          1,
          1,
          1,
          1,
          1,
          1,
          1,
          1,
          1,
          1
        ],
        "stroke": [
          "rgb(0,0,0)",
          "rgb(0,0,0)",
          "rgb(0,0,0)",
          "rgb(0,0,0)",
          "rgb(0,0,0)",
          "rgb(0,0,0)",
          "rgb(0,0,0)",
          "rgb(0,0,0)",
          "rgb(0,0,0)",
          "rgb(0,0,0)"
        ],
        "stroke-width": [
          1,
          1,
          1,
          1,
          1,
          1,
          1,
          1,
          1,
          1
        ],
        "shape": [
          "line",
          "line",
          "line",
          "line",
          "line",
          "line",
          "line",
          "line",
          "line",
          "line"
        ],
        "xPosition": [
          853,
          853,
          853,
          853,
          853,
          853,
          853,
          853,
          853,
          853
        ],
        "yPosition": [
          450,
          407,
          363,
          320,
          277,
          234,
          190,
          147,
          104,
          60
        ],
        "area": [
          0,
          0,
          0,
          0,
          0,
          0,
          0,
          0,
          0,
          0
        ],
        "width": [
          6,
          6,
          6,
          6,
          6,
          6,
          6,
          6,
          6,
          6
        ],
        "height": [
          0,
          0,
          0,
          0,
          0,
          0,
          0,
          0,
          0,
          0
        ],
        "rotation": [
          0,
          0,
          0,
          0,
          0,
          0,
          0,
          0,
          0,
          0
        ]
      },
      "nodeAttrs": [
        {
          "x2": "6",
          "y2": "0",
          "text": ""
        },
        {
          "x2": "6",
          "y2": "0",
          "text": ""
        },
        {
          "x2": "6",
          "y2": "0",
          "text": ""
        },
        {
          "x2": "6",
          "y2": "0",
          "text": ""
        },
        {
          "x2": "6",
          "y2": "0",
          "text": ""
        },
        {
          "x2": "6",
          "y2": "0",
          "text": ""
        },
        {
          "x2": "6",
          "y2": "0",
          "text": ""
        },
        {
          "x2": "6",
          "y2": "0",
          "text": ""
        },
        {
          "x2": "6",
          "y2": "0",
          "text": ""
        },
        {
          "x2": "6",
          "y2": "0",
          "text": ""
        }
      ],
      "axis": "yaxis",
      "name": "yaxis-ticks",
      "mappings": [
        {
          "type": "linear",
          "data": ["number"],
          "attr": "yPosition",
          "params": {
            "attrMin": 450.0363636363636,
            "coeffs": [
              -4.329696969696971e-8,
              450.0363636363636
            ],
            "err": 0.9999946705339781
          }
        },
        {
          "type": "linear",
          "data": ["deconID"],
          "attr": "yPosition",
          "params": {
            "attrMin": 450.03636363637133,
            "coeffs": [
              -14.432323232323155,
              4332.3313131313
            ],
            "err": 0.9999946705339781
          }
        }
      ]
    },
    {
      "schema": [
        "number",
        "deconID"
      ],
      "nodeType": "text",
      "ids": [
        270,
        273,
        276,
        279,
        282,
        285,
        288,
        291,
        294,
        297
      ],
      "data": {
        "number": [
          0,
          1000000000,
          2000000000,
          3000000000,
          4000000000,
          5000000000,
          6000000000,
          7000000000,
          8000000000,
          9000000000
        ],
        "deconID": [
          270,
          273,
          276,
          279,
          282,
          285,
          288,
          291,
          294,
          297
        ]
      },
      "attrs": {
        "font-family": [
          "Times",
          "Times",
          "Times",
          "Times",
          "Times",
          "Times",
          "Times",
          "Times",
          "Times",
          "Times"
        ],
        "font-size": [
          "12px",
          "12px",
          "12px",
          "12px",
          "12px",
          "12px",
          "12px",
          "12px",
          "12px",
          "12px"
        ],
        "opacity": [
          1,
          1,
          1,
          1,
          1,
          1,
          1,
          1,
          1,
          1
        ],
        "fill": [
          "rgb(0,0,0)",
          "rgb(0,0,0)",
          "rgb(0,0,0)",
          "rgb(0,0,0)",
          "rgb(0,0,0)",
          "rgb(0,0,0)",
          "rgb(0,0,0)",
          "rgb(0,0,0)",
          "rgb(0,0,0)",
          "rgb(0,0,0)"
        ],
        "fill-opacity": [
          1,
          1,
          1,
          1,
          1,
          1,
          1,
          1,
          1,
          1
        ],
        "stroke": [
          "none",
          "none",
          "none",
          "none",
          "none",
          "none",
          "none",
          "none",
          "none",
          "none"
        ],
        "stroke-width": [
          1,
          1,
          1,
          1,
          1,
          1,
          1,
          1,
          1,
          1
        ],
        "shape": [
          "text",
          "text",
          "text",
          "text",
          "text",
          "text",
          "text",
          "text",
          "text",
          "text"
        ],
        "xPosition": [
          862,
          893.5,
          893.5,
          893.5,
          893.5,
          893.5,
          893.5,
          893.5,
          893.5,
          893.5
        ],
        "yPosition": [
          450.8359375,
          407.8359375,
          363.8359375,
          320.8359375,
          277.8359375,
          234.8359375,
          190.8359375,
          147.8359375,
          104.8359375,
          60.8359375
        ],
        "area": [
          72.09375,
          829.078125,
          829.078125,
          829.078125,
          829.078125,
          829.078125,
          829.078125,
          829.078125,
          829.078125,
          829.078125
        ],
        "width": [
          6,
          69,
          69,
          69,
          69,
          69,
          69,
          69,
          69,
          69
        ],
        "height": [
          12.015625,
          12.015625,
          12.015625,
          12.015625,
          12.015625,
          12.015625,
          12.015625,
          12.015625,
          12.015625,
          12.015625
        ],
        "rotation": [
          0,
          0,
          0,
          0,
          0,
          0,
          0,
          0,
          0,
          0
        ]
      },
      "nodeAttrs": [
        {
          "dy": ".32em",
          "x": "9",
          "y": "0",
          "style": "text-anchor: start;",
          "text": "0"
        },
        {
          "dy": ".32em",
          "x": "9",
          "y": "0",
          "style": "text-anchor: start;",
          "text": "1,000,000,000"
        },
        {
          "dy": ".32em",
          "x": "9",
          "y": "0",
          "style": "text-anchor: start;",
          "text": "2,000,000,000"
        },
        {
          "dy": ".32em",
          "x": "9",
          "y": "0",
          "style": "text-anchor: start;",
          "text": "3,000,000,000"
        },
        {
          "dy": ".32em",
          "x": "9",
          "y": "0",
          "style": "text-anchor: start;",
          "text": "4,000,000,000"
        },
        {
          "dy": ".32em",
          "x": "9",
          "y": "0",
          "style": "text-anchor: start;",
          "text": "5,000,000,000"
        },
        {
          "dy": ".32em",
          "x": "9",
          "y": "0",
          "style": "text-anchor: start;",
          "text": "6,000,000,000"
        },
        {
          "dy": ".32em",
          "x": "9",
          "y": "0",
          "style": "text-anchor: start;",
          "text": "7,000,000,000"
        },
        {
          "dy": ".32em",
          "x": "9",
          "y": "0",
          "style": "text-anchor: start;",
          "text": "8,000,000,000"
        },
        {
          "dy": ".32em",
          "x": "9",
          "y": "0",
          "style": "text-anchor: start;",
          "text": "9,000,000,000"
        }
      ],
      "axis": "yaxis",
      "name": "yaxis-labels",
      "mappings": [
        {
          "type": "linear",
          "data": ["number"],
          "attr": "yPosition",
          "params": {
            "attrMin": 450.8723011363636,
            "coeffs": [
              -4.329696969696971e-8,
              450.8723011363636
            ],
            "err": 0.9999946705339781
          }
        },
        {
          "type": "linear",
          "data": ["deconID"],
          "attr": "yPosition",
          "params": {
            "attrMin": 450.87230113635223,
            "coeffs": [
              -14.432323232323228,
              4347.599573863624
            ],
            "err": 0.9999946705339781
          }
        }
      ]
    },
    {
      "schema": [
        "axis",
        "tick",
        "deconID",
        "lineID"
      ],
      "nodeType": "linePoint",
      "ids": [
        266,
        266,
        266,
        266
      ],
      "data": {
        "axis": [
          0,
          0,
          800,
          800
        ],
        "tick": [
          0,
          1,
          1,
          0
        ],
        "deconID": [
          266,
          266,
          266,
          266
        ],
        "lineID": [
          0,
          1,
          2,
          3
        ]
      },
      "attrs": {
        "font-family": [
          "Times",
          "Times",
          "Times",
          "Times"
        ],
        "font-size": [
          "16px",
          "16px",
          "16px",
          "16px"
        ],
        "opacity": [
          1,
          1,
          1,
          1
        ],
        "fill": [
          "rgb(0,0,0)",
          "rgb(0,0,0)",
          "rgb(0,0,0)",
          "rgb(0,0,0)"
        ],
        "fill-opacity": [
          1,
          1,
          1,
          1
        ],
        "stroke": [
          "none",
          "none",
          "none",
          "none"
        ],
        "stroke-width": [
          1,
          1,
          1,
          1
        ],
        "shape": [
          "linePoint",
          "linePoint",
          "linePoint",
          "linePoint"
        ],
        "xPosition": [
          50,
          50,
          850,
          850
        ],
        "yPosition": [
          451,
          450,
          450,
          451
        ],
        "area": [
          800,
          800,
          800,
          800
        ],
        "width": [
          800,
          800,
          800,
          800
        ],
        "height": [
          1,
          1,
          1,
          1
        ],
        "rotation": [
          0,
          0,
          0,
          0
        ]
      },
      "nodeAttrs": [
        {
          "class": "domain",
          "d": "M0,1V0H800V1",
          "text": ""
        },
        {
          "class": "domain",
          "d": "M0,1V0H800V1",
          "text": ""
        },
        {
          "class": "domain",
          "d": "M0,1V0H800V1",
          "text": ""
        },
        {
          "class": "domain",
          "d": "M0,1V0H800V1",
          "text": ""
        }
      ],
      "axis": "xaxis",
      "name": "xaxis-line",
      "mappings": [
        {
          "type": "linear",
          "data": ["axis"],
          "attr": "xPosition",
          "params": {
            "attrMin": 50,
            "coeffs": [
              1,
              50
            ],
            "err": 1
          }
        },
        {
          "type": "linear",
          "data": ["tick"],
          "attr": "yPosition",
          "params": {
            "attrMin": 451,
            "coeffs": [
              -1,
              451
            ],
            "err": 1
          }
        }
      ]
    },
    {
      "schema": [
        "domain",
        "tick",
        "deconID",
        "lineID"
      ],
      "nodeType": "linePoint",
      "ids": [
        298,
        298,
        298,
        298
      ],
      "data": {
        "domain": [
          9242083546,
          9242083546,
          0,
          0
        ],
        "tick": [
          0,
          1,
          1,
          0
        ],
        "deconID": [
          298,
          298,
          298,
          298
        ],
        "lineID": [
          0,
          1,
          2,
          3
        ]
      },
      "attrs": {
        "font-family": [
          "Times",
          "Times",
          "Times",
          "Times"
        ],
        "font-size": [
          "16px",
          "16px",
          "16px",
          "16px"
        ],
        "opacity": [
          1,
          1,
          1,
          1
        ],
        "fill": [
          "rgb(0,0,0)",
          "rgb(0,0,0)",
          "rgb(0,0,0)",
          "rgb(0,0,0)"
        ],
        "fill-opacity": [
          1,
          1,
          1,
          1
        ],
        "stroke": [
          "none",
          "none",
          "none",
          "none"
        ],
        "stroke-width": [
          1,
          1,
          1,
          1
        ],
        "shape": [
          "linePoint",
          "linePoint",
          "linePoint",
          "linePoint"
        ],
        "xPosition": [
          851,
          850,
          850,
          851
        ],
        "yPosition": [
          50,
          50,
          450,
          450
        ],
        "area": [
          400,
          400,
          400,
          400
        ],
        "width": [
          1,
          1,
          1,
          1
        ],
        "height": [
          400,
          400,
          400,
          400
        ],
        "rotation": [
          0,
          0,
          0,
          0
        ]
      },
      "nodeAttrs": [
        {
          "class": "domain",
          "d": "M1,0H0V400H1",
          "text": ""
        },
        {
          "class": "domain",
          "d": "M1,0H0V400H1",
          "text": ""
        },
        {
          "class": "domain",
          "d": "M1,0H0V400H1",
          "text": ""
        },
        {
          "class": "domain",
          "d": "M1,0H0V400H1",
          "text": ""
        }
      ],
      "axis": "yaxis",
      "name": "yaxis-line",
      "mappings": [
        {
          "type": "linear",
          "data": ["tick"],
          "attr": "xPosition",
          "params": {
            "attrMin": 851,
            "coeffs": [
              -1,
              851
            ],
            "err": 1
          }
        },
        {
          "type": "linear",
          "data": ["domain"],
          "attr": "yPosition",
          "params": {
            "attrMin": 450,
            "coeffs": [
              -4.328028393263347e-8,
              450
            ],
            "err": 1
          }
        }
      ]
    }
  ],
  "ids": [
    2,
    4,
    6,
    8,
    10,
    12,
    14,
    16,
    18,
    20,
    22,
    24,
    26,
    28,
    30,
    32,
    34,
    36,
    38,
    40,
    42,
    44,
    46,
    48,
    50,
    52,
    54,
    56,
    58,
    60,
    62,
    64,
    66,
    68,
    70,
    72,
    74,
    76,
    78,
    80,
    82,
    84,
    86,
    88,
    90,
    92,
    94,
    96,
    98,
    100,
    102,
    104,
    106,
    108,
    110,
    112,
    114,
    116,
    118,
    120,
    122,
    124,
    126,
    128,
    130,
    132,
    134,
    136,
    138,
    140,
    142,
    144,
    146,
    148,
    150,
    152,
    154,
    156,
    158,
    160,
    162,
    164,
    166,
    168,
    170,
    172,
    174,
    176,
    178,
    180,
    182,
    184,
    186,
    188,
    190,
    192,
    194,
    196,
    198,
    200,
    204,
    205,
    207,
    208,
    210,
    211,
    213,
    214,
    216,
    217,
    219,
    220,
    222,
    223,
    225,
    226,
    228,
    229,
    231,
    232,
    234,
    235,
    237,
    238,
    240,
    241,
    243,
    244,
    246,
    247,
    249,
    250,
    252,
    253,
    255,
    256,
    258,
    259,
    261,
    262,
    264,
    265,
    269,
    270,
    272,
    273,
    275,
    276,
    278,
    279,
    281,
    282,
    284,
    285,
    287,
    288,
    290,
    291,
    293,
    294,
    296,
    297,
    266,
    266,
    266,
    266,
    298,
    298,
    298,
    298
  ]
}